data/__init__.py
data/distroFile.xlsx
data/testInit.in
hydrogen/EventClass.py
hydrogen/HydroGen.py
hydrogen/__init__.py
hydrogen/tests/__init__.py
hydrogen/tests/test_HydroGen.py
hydrogen/tests/test_eventClass.py
hydrogen/tests/test_tools.py
hydrogen/tools/__init__.py
hydrogen/tools/methodChoice.py
hydrogen/tools/tools.py
hydrogen-2.2.2.dist-info/LICENSE
hydrogen-2.2.2.dist-info/METADATA
hydrogen-2.2.2.dist-info/WHEEL
hydrogen-2.2.2.dist-info/entry_points.txt
hydrogen-2.2.2.dist-info/top_level.txt
hydrogen-2.2.2.dist-info/RECORD
