Metadata-Version: 2.1
Name: hydrogen
Version: 2.2.2
Summary: Hydrograph generator: generate stochastic domestic water consumption events
Home-page: https://gitlab.com/brunohad/HydroGen2.0
Author: Bruno Hadengue
Author-email: bruno.hadengue@eawag.ch
License: GNU AGPLv3
Platform: UNKNOWN
Requires-Dist: matplotlib (<=2.2.5) ; python_version < "3.7"
Requires-Dist: scipy (<=1.2.3) ; python_version < "3.7"
Requires-Dist: pandas (<=0.24.2) ; python_version < "3.7"
Requires-Dist: numpy (<=1.16.6) ; python_version < "3.7"
Requires-Dist: pyparsing (<=2.4.7) ; python_version < "3.7"
Requires-Dist: xlrd (<2.0) ; python_version < "3.7"
Requires-Dist: argparse ; python_version < "3.7"
Requires-Dist: matplotlib (>=2.2.5) ; python_version >= "3.7"
Requires-Dist: scipy (>=1.6) ; python_version >= "3.7"
Requires-Dist: pandas (>=1.2.2) ; python_version >= "3.7"
Requires-Dist: numpy (>=1.20.1) ; python_version >= "3.7"
Requires-Dist: pyparsing (>=3.0.0b2) ; python_version >= "3.7"
Requires-Dist: openpyxl (>=3.0.6) ; python_version >= "3.7"
